rh/__init__.py
rh/core.py
rh/util.py
rh/functions/__init__.py
rh/generators/__init__.py
rh/generators/html.py
rh/spec/__init__.py
rh/templates/__init__.py
rh-0.0.11.dist-info/LICENSE
rh-0.0.11.dist-info/METADATA
rh-0.0.11.dist-info/WHEEL
rh-0.0.11.dist-info/top_level.txt
rh-0.0.11.dist-info/RECORD
