Metadata-Version: 2.1
Name: rh
Version: 0.0.11
Summary: Reactive Html Framework - Transform variable relationships into interactive web apps
Home-page: https://github.com/i2mint/rh
Author: OtoSense
Author-email: thor@otosense.ai
License: mit
Project-URL: Bug Reports, https://github.com/i2mint/rh/issues
Project-URL: Source, https://github.com/i2mint/rh
Project-URL: Documentation, https://github.com/i2mint/rh#readme
Keywords: reactive,html,web-apps,interactive,forms,javascript,mesh,reactive-programming,data-flow,rjsf,real-time,web-framework,ui-generation,declarative,computational-graph
Platform: any
Classifier: Development Status :: 3 - Alpha
Classifier: Intended Audience :: Developers
Classifier: Intended Audience :: Science/Research
Classifier: License :: OSI Approved :: MIT License
Classifier: Operating System :: OS Independent
Classifier: Programming Language :: Python :: 3.10
Classifier: Programming Language :: Python :: 3.11
Classifier: Programming Language :: Python :: 3.12
Classifier: Topic :: Software Development :: Libraries :: Python Modules
Classifier: Topic :: Internet :: WWW/HTTP :: Dynamic Content
Classifier: Topic :: Scientific/Engineering :: Visualization
Classifier: Topic :: Software Development :: User Interfaces
Requires-Python: >=3.8
License-File: LICENSE
Requires-Dist: config2py
Provides-Extra: dev
Requires-Dist: pytest>=7.0.0; extra == "dev"
Requires-Dist: pytest-cov>=3.0.0; extra == "dev"
Provides-Extra: docs
Provides-Extra: test
Requires-Dist: pytest>=7.0.0; extra == "test"
